collector/client.py
collector/middleware.py
requestresponsecollector-0.2.7.dist-info/METADATA
requestresponsecollector-0.2.7.dist-info/WHEEL
requestresponsecollector-0.2.7.dist-info/RECORD
