Metadata-Version: 2.1
Name: requestresponsecollector
Version: 0.2.7
Summary: 
Home-page: https://github.com/mnaile/RequestResponseCollector
Author: Naila
Author-email: mammadaliyevan@gmail.com
Requires-Python: >=3.8.2,<4.0.0
Classifier: Programming Language :: Python :: 3
Classifier: Programming Language :: Python :: 3.9
Classifier: Programming Language :: Python :: 3.10
Classifier: Programming Language :: Python :: 3.11
Classifier: Programming Language :: Python :: 3.12
Requires-Dist: aiohttp (>=3.8.6,<3.9.4)
Project-URL: Repository, https://github.com/mnaile/RequestResponseCollector
